bullmq/__init__.py
bullmq/backoffs.py
bullmq/error_code.py
bullmq/event_emitter.py
bullmq/flow_producer.py
bullmq/job.py
bullmq/queue.py
bullmq/queue_keys.py
bullmq/redis_connection.py
bullmq/scripts.py
bullmq/timer.py
bullmq/utils.py
bullmq/worker.py
bullmq/commands/addDelayedJob-6.lua
bullmq/commands/addParentJob-4.lua
bullmq/commands/addPrioritizedJob-7.lua
bullmq/commands/addStandardJob-7.lua
bullmq/commands/changeDelay-4.lua
bullmq/commands/changePriority-6.lua
bullmq/commands/cleanJobsInSet-2.lua
bullmq/commands/drain-4.lua
bullmq/commands/extendLock-2.lua
bullmq/commands/getCounts-1.lua
bullmq/commands/getRanges-1.lua
bullmq/commands/getState-8.lua
bullmq/commands/getStateV2-8.lua
bullmq/commands/isFinished-3.lua
bullmq/commands/isJobInList-1.lua
bullmq/commands/moveJobFromActiveToWait-10.lua
bullmq/commands/moveJobsToWait-7.lua
bullmq/commands/moveStalledJobsToWait-9.lua
bullmq/commands/moveToActive-11.lua
bullmq/commands/moveToDelayed-7.lua
bullmq/commands/moveToFinished-14.lua
bullmq/commands/moveToWaitingChildren-4.lua
bullmq/commands/obliterate-2.lua
bullmq/commands/paginate-1.lua
bullmq/commands/pause-7.lua
bullmq/commands/promote-8.lua
bullmq/commands/releaseLock-1.lua
bullmq/commands/removeChildDependency-1.lua
bullmq/commands/removeJob-1.lua
bullmq/commands/removeRepeatable-2.lua
bullmq/commands/reprocessJob-7.lua
bullmq/commands/retryJob-10.lua
bullmq/commands/saveStacktrace-1.lua
bullmq/commands/updateData-1.lua
bullmq/commands/updateProgress-3.lua
bullmq/custom_errors/__init__.py
bullmq/custom_errors/waiting_children_error.py
bullmq/types/__init__.py
bullmq/types/backoff_options.py
bullmq/types/job_options.py
bullmq/types/keep_jobs.py
bullmq/types/promote_jobs_options.py
bullmq/types/queue_options.py
bullmq/types/retry_jobs_options.py
bullmq/types/worker_options.py
bullmqmful-2.3.3.dist-info/METADATA
bullmqmful-2.3.3.dist-info/WHEEL
bullmqmful-2.3.3.dist-info/top_level.txt
bullmqmful-2.3.3.dist-info/RECORD
